{"start_time":1552939802000,"end_time":1552941183000,"created_at":1552939803000,"updated_at":1552941189000,"start_time_timezone_offset":39600000,"end_time_timezone_offset":39600000,"distance":3205,"duration":1380239,"elevation_gain":31,"elevation_loss":30,"average_speed":8.361,"calories":255,"longitude":151.69142,"latitude":-32.89684,"max_speed":10.88181,"pause_duration":0,"duration_per_km":430652,"temperature":18.0,"pulse_avg":0,"pulse_max":0,"avg_cadence":0,"max_cadence":0,"manual":false,"edited":false,"completed":true,"live_tracking_active":false,"live_tracking_enabled":true,"cheering_enabled":true,"indoor":false,"id":"75fc168d-8b4f-4b4d-ac91-2fe113a46354","weather_condition_id":"2","sport_type_id":"1"}