{"start_time":1531171745000,"end_time":1531173358000,"created_at":1531173392000,"updated_at":1531173392000,"start_time_timezone_offset":36000000,"end_time_timezone_offset":36000000,"distance":3519,"duration":1612060,"elevation_gain":76,"elevation_loss":86,"average_speed":7.859581,"calories":297,"longitude":151.694443,"latitude":-32.8963127,"max_speed":13.4666309,"duration_per_km":458102,"temperature":8.0,"manual":false,"edited":false,"completed":true,"live_tracking_active":false,"live_tracking_enabled":false,"cheering_enabled":false,"indoor":false,"id":"adbe9c67-4f4e-4629-9a5b-b68b796ceada","weather_condition_id":"2","sport_type_id":"1"}